README.rst
setup.cfg
setup.py
auth_proxy/auth_db.py
auth_proxy/auth_db.pyc
auth_proxy/auth_proxy.py
auth_proxy/auth_system.py
auth_proxy/auth_system.pyc
auth_proxy/federated_auth.sql
auth_proxy/key_server.py
auth_proxy/server_init.py
auth_proxy/ssh_gen.py
auth_proxy/tukey-test-server.py
auth_proxy/user_tools/__init__.py
auth_proxy/user_tools/tukey-confirm-id.py
auth_proxy/user_tools/tukey_confirm.py
bin/auth.sh
bin/django.sh
bin/glance.sh
bin/nova.sh
local/local_settings.py
local/local_settings.py.example
local/local_settings.pyc
tools/create_db.sh
tools/create_log.sh
tools/install_venv.py
tools/pip-requires
tools/rfc.sh
tools/test-requires
tools/with_venv.sh
tools/logrotate.d/tukey-api
tools/logrotate.d/tukey-auth
tukey_cli/README
tukey_cli/tukeyServer.py
tukey_cli/etc/README.txt
tukey_cli/etc/enabled/adler
tukey_cli/etc/enabled/loginadler
tukey_cli/etc/enabled/loginsullivan
tukey_cli/etc/enabled/sullivan
tukey_cli/jsonTransform/__init__.py
tukey_cli/jsonTransform/jsonTransform.py
tukey_cli/tests/testConfigParser.py
tukey_cli/tests/testJsonTransform.py
tukey_cli/tests/testTukeyCli.py
tukey_cli/tests/config/noCheck-creds.conf
tukey_cli/tests/config/noCredCommand.conf
tukey_cli/tests/config/test.conf
tukey_cli/tests/config/sites-enabled/instance.conf
tukey_cli/tests/config/sites-enabled/nova.conf
tukey_cli/tests/config/sites-enabled/nova2.conf
tukey_cli/tests/config/sites-enabled/test.conf
tukey_cli/tests/config/sites-enabled/test2.conf
tukey_cli/tests/scripts/eucaInstances.bat
tukey_cli/tests/scripts/fakeInstances.bat
tukey_cli/tests/scripts/false.bat
tukey_cli/tests/scripts/true.bat
tukey_cli/tools/README.txt
tukey_cli/tools/addTukeyUser.py
tukey_cli/tools/get_usage.py
tukey_cli/tools/eucalyptus/adler_flavors.py
tukey_cli/tools/eucalyptus/cloudTools.py
tukey_cli/tools/eucalyptus/cloudTools.pyc
tukey_cli/tools/eucalyptus/compute.py
tukey_cli/tools/eucalyptus/euca-describe-instances-json
tukey_cli/tools/eucalyptus/get_quota.py
tukey_middleware.egg-info/PKG-INFO
tukey_middleware.egg-info/SOURCES.txt
tukey_middleware.egg-info/dependency_links.txt
tukey_middleware.egg-info/not-zip-safe
tukey_middleware.egg-info/top_level.txt