Metadata-Version: 1.1
Name: tukey-middleware
Version: 0.2
Summary: Tukey Cloud Console Middleware.
Home-page: https://github.com/mtgreenway/tukey-middleware
Author: Open Cloud Consortium
Author-email: mgreenway@uchicago.edu
License: Apache 2.0
Platform: UNKNOWN
Classifier: Development Status :: 4 - Beta
Classifier: Intended Audience :: Developers
Classifier: License :: OSI Approved :: Apache Software License
Classifier: Operating System :: POSIX :: Linux
Classifier: Programming Language :: Python
Classifier: Topic :: Internet :: Proxy Servers
